azure_sdk_trim/__init__.py
azure_sdk_trim/azure_sdk_trim.py
azure_sdk_trim/test/__init__.py
azure_sdk_trim/test/test_azure_sdk_trim.py
azure_sdk_trim-0.2.2.dist-info/LICENSE
azure_sdk_trim-0.2.2.dist-info/METADATA
azure_sdk_trim-0.2.2.dist-info/WHEEL
azure_sdk_trim-0.2.2.dist-info/entry_points.txt
azure_sdk_trim-0.2.2.dist-info/top_level.txt
azure_sdk_trim-0.2.2.dist-info/RECORD
