Metadata-Version: 2.1
Name: azure-sdk-trim
Version: 0.2.2
Summary: Azure SDK Trim tool
Author: Clumio Inc.
License: Apache License
Project-URL: Homepage, https://github.com/clumio-code/azure-sdk-trim
Project-URL: Documentation, https://github.com/clumio-code/azure-sdk-trim?tab=readme-ov-file
Project-URL: Repository, https://github.com/clumio-code/azure-sdk-trim
Project-URL: Issues, https://github.com/clumio-code/azure-sdk-trim/issues
Project-URL: Changelog, https://github.com/clumio-code/azure-sdk-trim/releases
Keywords: azure,sdk,clumio
Requires-Python: >=3.8
License-File: LICENSE
Requires-Dist: humanize >=4.9.0
Provides-Extra: dev
Requires-Dist: black >=24.3.0 ; extra == 'dev'
Requires-Dist: build >=1.2.1 ; extra == 'dev'
Requires-Dist: gray >=0.14.0 ; extra == 'dev'
Requires-Dist: green >=4.0.1 ; extra == 'dev'
Requires-Dist: mypy >=1.9.0 ; extra == 'dev'
Requires-Dist: mypy-extensions >=1.0.0 ; extra == 'dev'
Requires-Dist: pyfakefs >=5.3.5 ; extra == 'dev'
Requires-Dist: pylint >=3.1.0 ; extra == 'dev'
Requires-Dist: pyupgrade >=3.15.2 ; extra == 'dev'
Requires-Dist: unify >=0.5 ; extra == 'dev'
